ai_voice_bot/__init__.py
ai_voice_bot/mbot.py
ai_voice_bot/tbot.py
ai_voice_bot/vbot.py
ai_voice_bot/client/TextRealtimeClient.py
ai_voice_bot/client/VoiceRealtimeClient.py
ai_voice_bot/client/__init__.py
ai_voice_bot/handlers/AudioHandler.py
ai_voice_bot/handlers/InputHandler.py
ai_voice_bot/handlers/__init__.py
ai_voice_bot/mock/MockAudioHandler.py
ai_voice_bot/mock/__init__.py
voice_bot/__init__.py
voice_bot/mbot.py
voice_bot/tbot.py
voice_bot/vbot.py
voice_bot/client/TextRealtimeClient.py
voice_bot/client/VoiceRealtimeClient.py
voice_bot/client/__init__.py
voice_bot/handlers/AudioHandler.py
voice_bot/handlers/InputHandler.py
voice_bot/handlers/__init__.py
voice_bot/mock/MockAudioHandler.py
voice_bot/mock/__init__.py
ai_voice_bot-1.0.1.dist-info/LICENSE
ai_voice_bot-1.0.1.dist-info/METADATA
ai_voice_bot-1.0.1.dist-info/WHEEL
ai_voice_bot-1.0.1.dist-info/entry_points.txt
ai_voice_bot-1.0.1.dist-info/top_level.txt
ai_voice_bot-1.0.1.dist-info/RECORD
